pyforma/__init__.py
pyforma/_ast/__init__.py
pyforma/_ast/expressions/__init__.py
pyforma/_ast/expressions/attribute_expression.py
pyforma/_ast/expressions/binop_expression.py
pyforma/_ast/expressions/call_expression.py
pyforma/_ast/expressions/dict_expression.py
pyforma/_ast/expressions/expression.py
pyforma/_ast/expressions/expression_impl.py
pyforma/_ast/expressions/for_expression.py
pyforma/_ast/expressions/identifier_expression.py
pyforma/_ast/expressions/if_expression.py
pyforma/_ast/expressions/index_expression.py
pyforma/_ast/expressions/lambda_expression.py
pyforma/_ast/expressions/list_expression.py
pyforma/_ast/expressions/template_expression.py
pyforma/_ast/expressions/unop_expression.py
pyforma/_ast/expressions/value_expression.py
pyforma/_ast/expressions/with_expression.py
pyforma/_ast/origin.py
pyforma/_parser/__init__.py
pyforma/_parser/alternation.py
pyforma/_parser/comment.py
pyforma/_parser/delimited.py
pyforma/_parser/digits.py
pyforma/_parser/enclosed.py
pyforma/_parser/environment.py
pyforma/_parser/eof.py
pyforma/_parser/expression.py
pyforma/_parser/expression_block.py
pyforma/_parser/floating_point_literal_expression.py
pyforma/_parser/identifier.py
pyforma/_parser/identifier_expression.py
pyforma/_parser/indirect.py
pyforma/_parser/integer_literal_expression.py
pyforma/_parser/literal.py
pyforma/_parser/lookahead.py
pyforma/_parser/munch.py
pyforma/_parser/negative_lookahead.py
pyforma/_parser/non_empty.py
pyforma/_parser/nothing.py
pyforma/_parser/option.py
pyforma/_parser/parse_context.py
pyforma/_parser/parse_result.py
pyforma/_parser/parser.py
pyforma/_parser/repetition.py
pyforma/_parser/sequence.py
pyforma/_parser/string_literal_expression.py
pyforma/_parser/switch.py
pyforma/_parser/template.py
pyforma/_parser/template_syntax_config.py
pyforma/_parser/text.py
pyforma/_parser/transform_result.py
pyforma/_parser/until.py
pyforma/_parser/whitespace.py
pyforma/_template.py
pyforma/_template_context.py
pyforma/_util/__init__.py
pyforma-0.7.0.dist-info/licenses/LICENSE
pyforma-0.7.0.dist-info/WHEEL
pyforma-0.7.0.dist-info/METADATA
pyforma-0.7.0.dist-info/RECORD
