Metadata-Version: 2.4
Name: pyforma
Version: 0.7.0
Summary: A python template engine
Keywords: templates,template-engine,string-substitution
Author: Jan Möller
Author-email: Jan Möller <drag-on@gmx.de>
License-Expression: MIT
License-File: LICENSE
Classifier: Development Status :: 3 - Alpha
Classifier: Intended Audience :: Developers
Classifier: License :: OSI Approved :: MIT License
Classifier: Operating System :: OS Independent
Classifier: Programming Language :: Python :: 3.13
Classifier: Topic :: Software Development :: Libraries
Classifier: Topic :: Text Processing
Classifier: Typing :: Typed
Requires-Dist: annotated-types>=0.7.0
Requires-Python: >=3.13
